tornadoweb/README.md
tornadoweb/__init__.py
tornadoweb/__init__.pyc
tornadoweb/app.py
tornadoweb/app.pyc
tornadoweb/config.py
tornadoweb/config.pyc
tornadoweb/project.zip
tornadoweb/tornadoweb_init.py
tornadoweb/utility.py
tornadoweb/utility.pyc
tornadoweb/web.py
tornadoweb/web.pyc
tornadoweb-0.0.21.dist-info/LICENSE
tornadoweb-0.0.21.dist-info/METADATA
tornadoweb-0.0.21.dist-info/WHEEL
tornadoweb-0.0.21.dist-info/entry_points.txt
tornadoweb-0.0.21.dist-info/top_level.txt
tornadoweb-0.0.21.dist-info/RECORD
