Metadata-Version: 2.1
Name: tornadoweb
Version: 0.0.21
Summary: tornado web
Home-page: https://github.com/9wfox/tornadoweb
Author: 9wfox
Author-email: 568628130@qq.com
License: UNKNOWN
Platform: UNKNOWN
Classifier: Programming Language :: Python :: 2
Classifier: Programming Language :: Python :: 3
Classifier: License :: OSI Approved :: MIT License
Classifier: Operating System :: OS Independent
Requires-Dist: tornado
